[
  {
    "timestamp": 1774775400000,
    "open": 66673.48,
    "high": 66696.25,
    "low": 66666.66,
    "close": 66696.24,
    "volume": 15.32363
  },
  {
    "timestamp": 1774775700000,
    "open": 66696.24,
    "high": 66726.14,
    "low": 66667.26,
    "close": 66667.26,
    "volume": 12.39079
  },
  {
    "timestamp": 1774776000000,
    "open": 66667.26,
    "high": 66667.26,
    "low": 66640.34,
    "close": 66648.93,
    "volume": 6.59797
  },
  {
    "timestamp": 1774776300000,
    "open": 66648.93,
    "high": 66679.36,
    "low": 66647.91,
    "close": 66673.6,
    "volume": 17.66896
  },
  {
    "timestamp": 1774776600000,
    "open": 66673.59,
    "high": 66697.25,
    "low": 66550,
    "close": 66555.48,
    "volume": 38.74412
  },
  {
    "timestamp": 1774776900000,
    "open": 66555.49,
    "high": 66599.25,
    "low": 66549.54,
    "close": 66598.42,
    "volume": 14.32894
  },
  {
    "timestamp": 1774777200000,
    "open": 66598.42,
    "high": 66612.2,
    "low": 66579.22,
    "close": 66581.57,
    "volume": 10.96722
  },
  {
    "timestamp": 1774777500000,
    "open": 66581.58,
    "high": 66628,
    "low": 66581.58,
    "close": 66615.54,
    "volume": 8.98134
  },
  {
    "timestamp": 1774777800000,
    "open": 66615.54,
    "high": 66630.58,
    "low": 66601.55,
    "close": 66630.58,
    "volume": 8.16759
  },
  {
    "timestamp": 1774778100000,
    "open": 66630.57,
    "high": 66642.07,
    "low": 66628.12,
    "close": 66634.01,
    "volume": 17.70207
  },
  {
    "timestamp": 1774778400000,
    "open": 66634.01,
    "high": 66634.02,
    "low": 66550.74,
    "close": 66550.74,
    "volume": 36.91127
  },
  {
    "timestamp": 1774778700000,
    "open": 66550.74,
    "high": 66564.13,
    "low": 66503.81,
    "close": 66540,
    "volume": 25.11076
  },
  {
    "timestamp": 1774779000000,
    "open": 66540,
    "high": 66558.18,
    "low": 66500.02,
    "close": 66548.07,
    "volume": 58.46447
  },
  {
    "timestamp": 1774779300000,
    "open": 66548.07,
    "high": 66557.38,
    "low": 66460.63,
    "close": 66469.96,
    "volume": 34.45939
  },
  {
    "timestamp": 1774779600000,
    "open": 66469.97,
    "high": 66505.17,
    "low": 66429.37,
    "close": 66468.91,
    "volume": 41.17862
  },
  {
    "timestamp": 1774779900000,
    "open": 66468.91,
    "high": 66510,
    "low": 66467.12,
    "close": 66468.21,
    "volume": 35.31433
  },
  {
    "timestamp": 1774780200000,
    "open": 66468.21,
    "high": 66488.21,
    "low": 66422.29,
    "close": 66422.3,
    "volume": 28.0462
  },
  {
    "timestamp": 1774780500000,
    "open": 66422.29,
    "high": 66549.54,
    "low": 66418,
    "close": 66536.38,
    "volume": 32.6116
  },
  {
    "timestamp": 1774780800000,
    "open": 66536.39,
    "high": 66545.09,
    "low": 66508,
    "close": 66545.09,
    "volume": 11.68234
  },
  {
    "timestamp": 1774781100000,
    "open": 66545.95,
    "high": 66573.41,
    "low": 66527.01,
    "close": 66552.54,
    "volume": 16.00274
  },
  {
    "timestamp": 1774781400000,
    "open": 66552.54,
    "high": 66573.4,
    "low": 66538.3,
    "close": 66538.31,
    "volume": 16.01069
  },
  {
    "timestamp": 1774781700000,
    "open": 66538.31,
    "high": 66551.68,
    "low": 66498.15,
    "close": 66502.79,
    "volume": 10.07259
  },
  {
    "timestamp": 1774782000000,
    "open": 66502.8,
    "high": 66682,
    "low": 66502.79,
    "close": 66682,
    "volume": 33.70019
  },
  {
    "timestamp": 1774782300000,
    "open": 66682,
    "high": 66861,
    "low": 66666.57,
    "close": 66771.99,
    "volume": 57.49826
  },
  {
    "timestamp": 1774782600000,
    "open": 66772,
    "high": 66820.54,
    "low": 66756.82,
    "close": 66767.96,
    "volume": 27.26924
  },
  {
    "timestamp": 1774782900000,
    "open": 66767.95,
    "high": 66810.88,
    "low": 66739,
    "close": 66810.88,
    "volume": 28.58898
  },
  {
    "timestamp": 1774783200000,
    "open": 66810.88,
    "high": 66853.55,
    "low": 66771.62,
    "close": 66822.99,
    "volume": 27.89801
  },
  {
    "timestamp": 1774783500000,
    "open": 66822.99,
    "high": 66853.66,
    "low": 66806.74,
    "close": 66834.02,
    "volume": 11.56328
  },
  {
    "timestamp": 1774783800000,
    "open": 66834.02,
    "high": 66860,
    "low": 66767.39,
    "close": 66810.99,
    "volume": 18.04156
  },
  {
    "timestamp": 1774784100000,
    "open": 66810.98,
    "high": 66904.68,
    "low": 66810.98,
    "close": 66875.2,
    "volume": 20.26246
  },
  {
    "timestamp": 1774784400000,
    "open": 66875.2,
    "high": 66923.81,
    "low": 66846.39,
    "close": 66903.98,
    "volume": 29.14772
  },
  {
    "timestamp": 1774784700000,
    "open": 66903.98,
    "high": 66988.01,
    "low": 66824.67,
    "close": 66824.68,
    "volume": 48.42291
  },
  {
    "timestamp": 1774785000000,
    "open": 66824.68,
    "high": 66867.31,
    "low": 66801.32,
    "close": 66838.84,
    "volume": 18.4844
  },
  {
    "timestamp": 1774785300000,
    "open": 66838.84,
    "high": 66838.84,
    "low": 66816,
    "close": 66816.28,
    "volume": 15.78575
  },
  {
    "timestamp": 1774785600000,
    "open": 66816.29,
    "high": 66851.58,
    "low": 66797.37,
    "close": 66797.37,
    "volume": 13.08492
  },
  {
    "timestamp": 1774785900000,
    "open": 66797.37,
    "high": 66813.87,
    "low": 66781.32,
    "close": 66781.33,
    "volume": 8.553
  },
  {
    "timestamp": 1774786200000,
    "open": 66781.33,
    "high": 66814.8,
    "low": 66770.55,
    "close": 66773.06,
    "volume": 12.17938
  },
  {
    "timestamp": 1774786500000,
    "open": 66773.05,
    "high": 66816.31,
    "low": 66729.65,
    "close": 66782.74,
    "volume": 24.01576
  },
  {
    "timestamp": 1774786800000,
    "open": 66782.74,
    "high": 66784.5,
    "low": 66746.56,
    "close": 66784.5,
    "volume": 16.82887
  },
  {
    "timestamp": 1774787100000,
    "open": 66784.5,
    "high": 66800,
    "low": 66775.85,
    "close": 66781.62,
    "volume": 13.16997
  },
  {
    "timestamp": 1774787400000,
    "open": 66781.63,
    "high": 66805.16,
    "low": 66703.07,
    "close": 66722.67,
    "volume": 13.18348
  },
  {
    "timestamp": 1774787700000,
    "open": 66722.66,
    "high": 66757.39,
    "low": 66722.66,
    "close": 66755.39,
    "volume": 12.74695
  },
  {
    "timestamp": 1774788000000,
    "open": 66755.39,
    "high": 66787.46,
    "low": 66729.55,
    "close": 66738,
    "volume": 26.02837
  },
  {
    "timestamp": 1774788300000,
    "open": 66738,
    "high": 66817.61,
    "low": 66729.27,
    "close": 66803.91,
    "volume": 16.98836
  },
  {
    "timestamp": 1774788600000,
    "open": 66803.91,
    "high": 66870.34,
    "low": 66801.18,
    "close": 66860.47,
    "volume": 18.52664
  },
  {
    "timestamp": 1774788900000,
    "open": 66860.47,
    "high": 66862.73,
    "low": 66835.93,
    "close": 66849.88,
    "volume": 10.55079
  },
  {
    "timestamp": 1774789200000,
    "open": 66849.88,
    "high": 66875.24,
    "low": 66823.96,
    "close": 66823.96,
    "volume": 36.64492
  },
  {
    "timestamp": 1774789500000,
    "open": 66823.97,
    "high": 66823.97,
    "low": 66524.28,
    "close": 66542.88,
    "volume": 108.7079
  },
  {
    "timestamp": 1774789800000,
    "open": 66542.88,
    "high": 66622.21,
    "low": 66536.23,
    "close": 66606.37,
    "volume": 42.02395
  },
  {
    "timestamp": 1774790100000,
    "open": 66606.38,
    "high": 66666.93,
    "low": 66561.54,
    "close": 66648,
    "volume": 23.49152
  },
  {
    "timestamp": 1774790400000,
    "open": 66647.99,
    "high": 66699.75,
    "low": 66610.53,
    "close": 66646.4,
    "volume": 36.10873
  },
  {
    "timestamp": 1774790700000,
    "open": 66646.39,
    "high": 66647.47,
    "low": 66620,
    "close": 66628,
    "volume": 8.16821
  },
  {
    "timestamp": 1774791000000,
    "open": 66627.99,
    "high": 66687.3,
    "low": 66627.99,
    "close": 66636.86,
    "volume": 20.17684
  },
  {
    "timestamp": 1774791300000,
    "open": 66636.86,
    "high": 66686.39,
    "low": 66610,
    "close": 66686.38,
    "volume": 18.88893
  },
  {
    "timestamp": 1774791600000,
    "open": 66686.38,
    "high": 66686.39,
    "low": 66663.25,
    "close": 66669.94,
    "volume": 11.47404
  },
  {
    "timestamp": 1774791900000,
    "open": 66669.95,
    "high": 66686.48,
    "low": 66583.03,
    "close": 66611.06,
    "volume": 14.9985
  },
  {
    "timestamp": 1774792200000,
    "open": 66611.65,
    "high": 66648.42,
    "low": 66598.79,
    "close": 66620.35,
    "volume": 8.99667
  },
  {
    "timestamp": 1774792500000,
    "open": 66620.36,
    "high": 66633.26,
    "low": 66544.1,
    "close": 66580.36,
    "volume": 29.88369
  },
  {
    "timestamp": 1774792800000,
    "open": 66580.36,
    "high": 66600.09,
    "low": 66490,
    "close": 66502.58,
    "volume": 106.85794
  },
  {
    "timestamp": 1774793100000,
    "open": 66502.59,
    "high": 66529.5,
    "low": 66461,
    "close": 66522.75,
    "volume": 23.12889
  },
  {
    "timestamp": 1774793400000,
    "open": 66522.74,
    "high": 66797.01,
    "low": 66522.74,
    "close": 66672.92,
    "volume": 56.42014
  },
  {
    "timestamp": 1774793700000,
    "open": 66672.92,
    "high": 66691.72,
    "low": 66608.81,
    "close": 66617.14,
    "volume": 16.10196
  },
  {
    "timestamp": 1774794000000,
    "open": 66617.14,
    "high": 66647.38,
    "low": 66592.59,
    "close": 66597.88,
    "volume": 12.63616
  },
  {
    "timestamp": 1774794300000,
    "open": 66597.89,
    "high": 66597.93,
    "low": 66527,
    "close": 66538.5,
    "volume": 25.60536
  },
  {
    "timestamp": 1774794600000,
    "open": 66538.5,
    "high": 66594.39,
    "low": 66513.93,
    "close": 66588.89,
    "volume": 13.07949
  },
  {
    "timestamp": 1774794900000,
    "open": 66588.9,
    "high": 66617.14,
    "low": 66560.41,
    "close": 66560.42,
    "volume": 19.89954
  },
  {
    "timestamp": 1774795200000,
    "open": 66560.42,
    "high": 66580.03,
    "low": 66510.87,
    "close": 66574.96,
    "volume": 37.41243
  },
  {
    "timestamp": 1774795500000,
    "open": 66574.96,
    "high": 66579.31,
    "low": 66506.32,
    "close": 66551.24,
    "volume": 22.73261
  },
  {
    "timestamp": 1774795800000,
    "open": 66551.24,
    "high": 66579.21,
    "low": 66543.16,
    "close": 66553.07,
    "volume": 23.5976
  },
  {
    "timestamp": 1774796100000,
    "open": 66553.06,
    "high": 66595.33,
    "low": 66544.4,
    "close": 66589.64,
    "volume": 15.42447
  },
  {
    "timestamp": 1774796400000,
    "open": 66589.64,
    "high": 66730.6,
    "low": 66589.64,
    "close": 66630.54,
    "volume": 44.64322
  },
  {
    "timestamp": 1774796700000,
    "open": 66630.54,
    "high": 66710.05,
    "low": 66607.3,
    "close": 66616.61,
    "volume": 57.86146
  },
  {
    "timestamp": 1774797000000,
    "open": 66616.61,
    "high": 66646.67,
    "low": 66516.35,
    "close": 66597.3,
    "volume": 18.40861
  },
  {
    "timestamp": 1774797300000,
    "open": 66597.96,
    "high": 66670.33,
    "low": 66563.37,
    "close": 66576.44,
    "volume": 32.97769
  },
  {
    "timestamp": 1774797600000,
    "open": 66576.44,
    "high": 66576.44,
    "low": 66512.53,
    "close": 66516.83,
    "volume": 22.55842
  },
  {
    "timestamp": 1774797900000,
    "open": 66516.83,
    "high": 66516.83,
    "low": 66336.8,
    "close": 66420.74,
    "volume": 70.1241
  },
  {
    "timestamp": 1774798200000,
    "open": 66420.74,
    "high": 66436.37,
    "low": 66334.37,
    "close": 66413.04,
    "volume": 21.93554
  },
  {
    "timestamp": 1774798500000,
    "open": 66413.04,
    "high": 66435.12,
    "low": 66336.94,
    "close": 66392.73,
    "volume": 107.25939
  },
  {
    "timestamp": 1774798800000,
    "open": 66392.73,
    "high": 66465.4,
    "low": 66392.73,
    "close": 66456.12,
    "volume": 90.28842
  },
  {
    "timestamp": 1774799100000,
    "open": 66456.12,
    "high": 66486.65,
    "low": 66430,
    "close": 66436.9,
    "volume": 21.26262
  },
  {
    "timestamp": 1774799400000,
    "open": 66436.9,
    "high": 66543.24,
    "low": 66423.61,
    "close": 66540.42,
    "volume": 21.41063
  },
  {
    "timestamp": 1774799700000,
    "open": 66540.42,
    "high": 66540.43,
    "low": 66506.64,
    "close": 66523,
    "volume": 9.54088
  },
  {
    "timestamp": 1774800000000,
    "open": 66523.01,
    "high": 66558.11,
    "low": 66491.01,
    "close": 66492.27,
    "volume": 24.24119
  },
  {
    "timestamp": 1774800300000,
    "open": 66492.27,
    "high": 66506,
    "low": 66445.89,
    "close": 66506,
    "volume": 20.59296
  },
  {
    "timestamp": 1774800600000,
    "open": 66506,
    "high": 66529.45,
    "low": 66445.89,
    "close": 66447.22,
    "volume": 12.28665
  },
  {
    "timestamp": 1774800900000,
    "open": 66447.23,
    "high": 66665.05,
    "low": 66435.75,
    "close": 66632.3,
    "volume": 42.92199
  },
  {
    "timestamp": 1774801200000,
    "open": 66632.3,
    "high": 66661.75,
    "low": 66600,
    "close": 66604.58,
    "volume": 21.97248
  },
  {
    "timestamp": 1774801500000,
    "open": 66604.58,
    "high": 66631.23,
    "low": 66602.48,
    "close": 66617.19,
    "volume": 13.03842
  },
  {
    "timestamp": 1774801800000,
    "open": 66617.2,
    "high": 66618.94,
    "low": 66587.76,
    "close": 66590.24,
    "volume": 13.65195
  },
  {
    "timestamp": 1774802100000,
    "open": 66590.24,
    "high": 66590.24,
    "low": 66531.51,
    "close": 66559.79,
    "volume": 34.93184
  },
  {
    "timestamp": 1774802400000,
    "open": 66559.8,
    "high": 66567.7,
    "low": 66540,
    "close": 66540,
    "volume": 11.9142
  },
  {
    "timestamp": 1774802700000,
    "open": 66540,
    "high": 66560.26,
    "low": 66514.45,
    "close": 66536,
    "volume": 19.26623
  },
  {
    "timestamp": 1774803000000,
    "open": 66536,
    "high": 66567.93,
    "low": 66488.01,
    "close": 66493.08,
    "volume": 10.80932
  },
  {
    "timestamp": 1774803300000,
    "open": 66493.08,
    "high": 66525.86,
    "low": 66488.01,
    "close": 66499.35,
    "volume": 6.93582
  },
  {
    "timestamp": 1774803600000,
    "open": 66499.36,
    "high": 66518.63,
    "low": 66470.26,
    "close": 66482.15,
    "volume": 26.04109
  },
  {
    "timestamp": 1774803900000,
    "open": 66482.16,
    "high": 66546,
    "low": 66482.15,
    "close": 66536.83,
    "volume": 9.37783
  },
  {
    "timestamp": 1774804200000,
    "open": 66536.83,
    "high": 66536.84,
    "low": 66404.68,
    "close": 66422.35,
    "volume": 12.4284
  },
  {
    "timestamp": 1774804500000,
    "open": 66422.36,
    "high": 66422.36,
    "low": 66349.14,
    "close": 66349.14,
    "volume": 28.22409
  },
  {
    "timestamp": 1774804800000,
    "open": 66349.14,
    "high": 66349.14,
    "low": 66158.26,
    "close": 66200.3,
    "volume": 106.99776
  },
  {
    "timestamp": 1774805100000,
    "open": 66200.3,
    "high": 66267.3,
    "low": 66189.83,
    "close": 66262.41,
    "volume": 33.61398
  },
  {
    "timestamp": 1774805400000,
    "open": 66262.41,
    "high": 66295.77,
    "low": 66233.42,
    "close": 66295.76,
    "volume": 18.52026
  },
  {
    "timestamp": 1774805700000,
    "open": 66295.77,
    "high": 66326.26,
    "low": 66267.77,
    "close": 66304.17,
    "volume": 18.0863
  },
  {
    "timestamp": 1774806000000,
    "open": 66304.16,
    "high": 66422.43,
    "low": 66300.93,
    "close": 66392.26,
    "volume": 28.0055
  },
  {
    "timestamp": 1774806300000,
    "open": 66392.26,
    "high": 66392.27,
    "low": 66356.05,
    "close": 66376.79,
    "volume": 18.30073
  },
  {
    "timestamp": 1774806600000,
    "open": 66376.8,
    "high": 66435.48,
    "low": 66376.79,
    "close": 66390.44,
    "volume": 17.81756
  },
  {
    "timestamp": 1774806900000,
    "open": 66390.44,
    "high": 66398.63,
    "low": 66375.23,
    "close": 66385.84,
    "volume": 11.74281
  },
  {
    "timestamp": 1774807200000,
    "open": 66385.84,
    "high": 66408.98,
    "low": 66338.37,
    "close": 66338.38,
    "volume": 10.75605
  },
  {
    "timestamp": 1774807500000,
    "open": 66338.37,
    "high": 66369.42,
    "low": 66321.66,
    "close": 66349.84,
    "volume": 11.09442
  },
  {
    "timestamp": 1774807800000,
    "open": 66349.84,
    "high": 66417,
    "low": 66349.84,
    "close": 66402.54,
    "volume": 13.37264
  },
  {
    "timestamp": 1774808100000,
    "open": 66402.54,
    "high": 66463.89,
    "low": 66394.64,
    "close": 66438.94,
    "volume": 14.47356
  },
  {
    "timestamp": 1774808400000,
    "open": 66438.94,
    "high": 66445.9,
    "low": 66361.34,
    "close": 66391.34,
    "volume": 15.68485
  },
  {
    "timestamp": 1774808700000,
    "open": 66391.34,
    "high": 66430.38,
    "low": 66391.34,
    "close": 66397.51,
    "volume": 6.60365
  },
  {
    "timestamp": 1774809000000,
    "open": 66397.5,
    "high": 66425.11,
    "low": 66397.5,
    "close": 66409.63,
    "volume": 5.69182
  },
  {
    "timestamp": 1774809300000,
    "open": 66409.64,
    "high": 66540.43,
    "low": 66409.64,
    "close": 66486.44,
    "volume": 20.73472
  },
  {
    "timestamp": 1774809600000,
    "open": 66486.44,
    "high": 66493.96,
    "low": 66430.58,
    "close": 66430.59,
    "volume": 9.44536
  },
  {
    "timestamp": 1774809900000,
    "open": 66430.58,
    "high": 66457.92,
    "low": 66390.97,
    "close": 66439.87,
    "volume": 8.07845
  },
  {
    "timestamp": 1774810200000,
    "open": 66439.88,
    "high": 66463.35,
    "low": 66439.87,
    "close": 66450.9,
    "volume": 10.55471
  },
  {
    "timestamp": 1774810500000,
    "open": 66450.89,
    "high": 66462.08,
    "low": 66422.57,
    "close": 66427.26,
    "volume": 20.9399
  },
  {
    "timestamp": 1774810800000,
    "open": 66427.27,
    "high": 66431.13,
    "low": 66390.43,
    "close": 66428.02,
    "volume": 11.21507
  },
  {
    "timestamp": 1774811100000,
    "open": 66428.03,
    "high": 66450,
    "low": 66412.24,
    "close": 66412.24,
    "volume": 9.45442
  },
  {
    "timestamp": 1774811400000,
    "open": 66412.25,
    "high": 66437.61,
    "low": 66412,
    "close": 66436.9,
    "volume": 11.40572
  },
  {
    "timestamp": 1774811700000,
    "open": 66436.89,
    "high": 66463.35,
    "low": 66415.33,
    "close": 66449.05,
    "volume": 15.62771
  },
  {
    "timestamp": 1774812000000,
    "open": 66449.05,
    "high": 66477.2,
    "low": 66402.25,
    "close": 66407.39,
    "volume": 39.3415
  },
  {
    "timestamp": 1774812300000,
    "open": 66407.38,
    "high": 66437.76,
    "low": 66397.29,
    "close": 66425.94,
    "volume": 61.54138
  },
  {
    "timestamp": 1774812600000,
    "open": 66425.95,
    "high": 66477.81,
    "low": 66421.41,
    "close": 66477.81,
    "volume": 10.75844
  },
  {
    "timestamp": 1774812900000,
    "open": 66477.8,
    "high": 66477.8,
    "low": 66386.53,
    "close": 66386.53,
    "volume": 19.92692
  },
  {
    "timestamp": 1774813200000,
    "open": 66386.54,
    "high": 66399.36,
    "low": 66337.32,
    "close": 66391.74,
    "volume": 45.43436
  },
  {
    "timestamp": 1774813500000,
    "open": 66391.73,
    "high": 66426.09,
    "low": 66378.45,
    "close": 66378.45,
    "volume": 34.64351
  },
  {
    "timestamp": 1774813800000,
    "open": 66378.46,
    "high": 66378.46,
    "low": 66342.25,
    "close": 66364.8,
    "volume": 12.89048
  },
  {
    "timestamp": 1774814100000,
    "open": 66364.8,
    "high": 66364.81,
    "low": 66323.3,
    "close": 66348.62,
    "volume": 13.4342
  },
  {
    "timestamp": 1774814400000,
    "open": 66348.61,
    "high": 66431.53,
    "low": 66348.61,
    "close": 66431.52,
    "volume": 10.93264
  },
  {
    "timestamp": 1774814700000,
    "open": 66431.52,
    "high": 66511.9,
    "low": 66417.25,
    "close": 66471.32,
    "volume": 28.0988
  },
  {
    "timestamp": 1774815000000,
    "open": 66471.33,
    "high": 66475.75,
    "low": 66448.87,
    "close": 66461.17,
    "volume": 6.78899
  },
  {
    "timestamp": 1774815300000,
    "open": 66461.17,
    "high": 66579.31,
    "low": 66461.17,
    "close": 66554,
    "volume": 46.49699
  },
  {
    "timestamp": 1774815600000,
    "open": 66554,
    "high": 66793.83,
    "low": 66553.6,
    "close": 66721.52,
    "volume": 94.67496
  },
  {
    "timestamp": 1774815900000,
    "open": 66721.52,
    "high": 66759.33,
    "low": 66683.49,
    "close": 66705.65,
    "volume": 15.05401
  },
  {
    "timestamp": 1774816200000,
    "open": 66705.64,
    "high": 66719,
    "low": 66674.94,
    "close": 66681.1,
    "volume": 12.12947
  },
  {
    "timestamp": 1774816500000,
    "open": 66681.1,
    "high": 66696.04,
    "low": 66653.18,
    "close": 66653.18,
    "volume": 7.27348
  },
  {
    "timestamp": 1774816800000,
    "open": 66653.19,
    "high": 66660.21,
    "low": 66596.26,
    "close": 66596.27,
    "volume": 11.33759
  },
  {
    "timestamp": 1774817100000,
    "open": 66596.27,
    "high": 66626.72,
    "low": 66566.26,
    "close": 66580.38,
    "volume": 27.04803
  },
  {
    "timestamp": 1774817400000,
    "open": 66580.39,
    "high": 66593.78,
    "low": 66574.21,
    "close": 66586.68,
    "volume": 9.96712
  },
  {
    "timestamp": 1774817700000,
    "open": 66586.67,
    "high": 66615.78,
    "low": 66585.5,
    "close": 66614.05,
    "volume": 10.25293
  },
  {
    "timestamp": 1774818000000,
    "open": 66614.04,
    "high": 66672,
    "low": 66601.69,
    "close": 66601.7,
    "volume": 26.50726
  },
  {
    "timestamp": 1774818300000,
    "open": 66601.7,
    "high": 66611.9,
    "low": 66558.3,
    "close": 66558.3,
    "volume": 20.69822
  },
  {
    "timestamp": 1774818600000,
    "open": 66558.3,
    "high": 66568.3,
    "low": 66509.41,
    "close": 66554.62,
    "volume": 28.89933
  },
  {
    "timestamp": 1774818900000,
    "open": 66554.61,
    "high": 66560.4,
    "low": 66533.78,
    "close": 66543.4,
    "volume": 6.15115
  },
  {
    "timestamp": 1774819200000,
    "open": 66543.39,
    "high": 66595.1,
    "low": 66543.39,
    "close": 66595.1,
    "volume": 8.43074
  },
  {
    "timestamp": 1774819500000,
    "open": 66595.1,
    "high": 66675.96,
    "low": 66591.66,
    "close": 66653.87,
    "volume": 23.76876
  },
  {
    "timestamp": 1774819800000,
    "open": 66653.87,
    "high": 66695.1,
    "low": 66636.63,
    "close": 66649.88,
    "volume": 19.99782
  },
  {
    "timestamp": 1774820100000,
    "open": 66649.88,
    "high": 66672.03,
    "low": 66638.98,
    "close": 66638.98,
    "volume": 12.91558
  },
  {
    "timestamp": 1774820400000,
    "open": 66638.99,
    "high": 66640.33,
    "low": 66602.61,
    "close": 66640.32,
    "volume": 17.31932
  },
  {
    "timestamp": 1774820700000,
    "open": 66640.33,
    "high": 66695.17,
    "low": 66640.32,
    "close": 66688.41,
    "volume": 9.38308
  },
  {
    "timestamp": 1774821000000,
    "open": 66688.42,
    "high": 66697.42,
    "low": 66653.62,
    "close": 66697.42,
    "volume": 11.07913
  },
  {
    "timestamp": 1774821300000,
    "open": 66697.42,
    "high": 66756.51,
    "low": 66681.27,
    "close": 66710.12,
    "volume": 34.95608
  },
  {
    "timestamp": 1774821600000,
    "open": 66710.12,
    "high": 66710.12,
    "low": 66360.85,
    "close": 66397.06,
    "volume": 72.32828
  },
  {
    "timestamp": 1774821900000,
    "open": 66397.07,
    "high": 66428.01,
    "low": 66259.25,
    "close": 66402.25,
    "volume": 48.69028
  },
  {
    "timestamp": 1774822200000,
    "open": 66402.26,
    "high": 66445.9,
    "low": 66229.99,
    "close": 66306.35,
    "volume": 52.55086
  },
  {
    "timestamp": 1774822500000,
    "open": 66306.34,
    "high": 66386.15,
    "low": 66272,
    "close": 66327.42,
    "volume": 28.11086
  },
  {
    "timestamp": 1774822800000,
    "open": 66327.42,
    "high": 66491.12,
    "low": 66305.26,
    "close": 66416.84,
    "volume": 26.04416
  },
  {
    "timestamp": 1774823100000,
    "open": 66416.84,
    "high": 66416.84,
    "low": 66352,
    "close": 66384.51,
    "volume": 18.73569
  },
  {
    "timestamp": 1774823400000,
    "open": 66384.51,
    "high": 66425.85,
    "low": 66342.25,
    "close": 66379.38,
    "volume": 20.86366
  },
  {
    "timestamp": 1774823700000,
    "open": 66379.38,
    "high": 66396.32,
    "low": 66185.78,
    "close": 66255.08,
    "volume": 176.55077
  },
  {
    "timestamp": 1774824000000,
    "open": 66255.08,
    "high": 66270.62,
    "low": 65638.44,
    "close": 65684.25,
    "volume": 443.44915
  },
  {
    "timestamp": 1774824300000,
    "open": 65684.24,
    "high": 65684.25,
    "low": 65000,
    "close": 65045.73,
    "volume": 932.60654
  },
  {
    "timestamp": 1774824600000,
    "open": 65045.73,
    "high": 65466,
    "low": 65000,
    "close": 65465.48,
    "volume": 203.98932
  },
  {
    "timestamp": 1774824900000,
    "open": 65465.47,
    "high": 65983.35,
    "low": 65452.01,
    "close": 65860.31,
    "volume": 195.20022
  },
  {
    "timestamp": 1774825200000,
    "open": 65860.31,
    "high": 66382.98,
    "low": 65859.91,
    "close": 66035.69,
    "volume": 251.0425
  },
  {
    "timestamp": 1774825500000,
    "open": 66035.68,
    "high": 66151.54,
    "low": 65973.22,
    "close": 66064.43,
    "volume": 109.02174
  },
  {
    "timestamp": 1774825800000,
    "open": 66064.43,
    "high": 66134.97,
    "low": 66014.21,
    "close": 66102.11,
    "volume": 39.46066
  },
  {
    "timestamp": 1774826100000,
    "open": 66102.12,
    "high": 66270.35,
    "low": 66080.19,
    "close": 66124.23,
    "volume": 73.53364
  },
  {
    "timestamp": 1774826400000,
    "open": 66124.23,
    "high": 66305.22,
    "low": 66046,
    "close": 66080.24,
    "volume": 55.88178
  },
  {
    "timestamp": 1774826700000,
    "open": 66080.24,
    "high": 66080.24,
    "low": 65960.9,
    "close": 66010.01,
    "volume": 49.16038
  },
  {
    "timestamp": 1774827000000,
    "open": 66010.01,
    "high": 66094.64,
    "low": 65944.18,
    "close": 65972.31,
    "volume": 68.23052
  },
  {
    "timestamp": 1774827300000,
    "open": 65972.31,
    "high": 65992.87,
    "low": 65868.79,
    "close": 65934.46,
    "volume": 60.87864
  },
  {
    "timestamp": 1774827600000,
    "open": 65934.45,
    "high": 66039.02,
    "low": 65914.59,
    "close": 66029.24,
    "volume": 62.03676
  },
  {
    "timestamp": 1774827900000,
    "open": 66029.24,
    "high": 66168.42,
    "low": 66017.38,
    "close": 66033.07,
    "volume": 51.84531
  },
  {
    "timestamp": 1774828200000,
    "open": 66033.07,
    "high": 66059.39,
    "low": 65885.13,
    "close": 66059.38,
    "volume": 75.33994
  },
  {
    "timestamp": 1774828500000,
    "open": 66059.39,
    "high": 66069.77,
    "low": 66000.76,
    "close": 66010.93,
    "volume": 34.08555
  },
  {
    "timestamp": 1774828800000,
    "open": 66010.93,
    "high": 66086.94,
    "low": 65866.66,
    "close": 65866.66,
    "volume": 38.89284
  },
  {
    "timestamp": 1774829100000,
    "open": 65866.66,
    "high": 66010.34,
    "low": 65802,
    "close": 65880.58,
    "volume": 66.16275
  },
  {
    "timestamp": 1774829400000,
    "open": 65880.57,
    "high": 65921.73,
    "low": 65846.28,
    "close": 65853.46,
    "volume": 24.68612
  },
  {
    "timestamp": 1774829700000,
    "open": 65853.46,
    "high": 66930.63,
    "low": 65800.59,
    "close": 66908.53,
    "volume": 327.90203
  },
  {
    "timestamp": 1774830000000,
    "open": 66908.52,
    "high": 67059.66,
    "low": 66608.09,
    "close": 66609.54,
    "volume": 367.38591
  },
  {
    "timestamp": 1774830300000,
    "open": 66609.54,
    "high": 66860.47,
    "low": 66540.44,
    "close": 66574.21,
    "volume": 103.18283
  },
  {
    "timestamp": 1774830600000,
    "open": 66574.21,
    "high": 66740.69,
    "low": 66475.5,
    "close": 66507.64,
    "volume": 85.01155
  },
  {
    "timestamp": 1774830900000,
    "open": 66507.64,
    "high": 66561.54,
    "low": 66250,
    "close": 66294.17,
    "volume": 78.44614
  },
  {
    "timestamp": 1774831200000,
    "open": 66295.67,
    "high": 66336.33,
    "low": 66192.73,
    "close": 66331.53,
    "volume": 79.80403
  },
  {
    "timestamp": 1774831500000,
    "open": 66331.53,
    "high": 66419.35,
    "low": 66303.58,
    "close": 66328.38,
    "volume": 60.54982
  },
  {
    "timestamp": 1774831800000,
    "open": 66328.39,
    "high": 66339.83,
    "low": 66111.11,
    "close": 66183.37,
    "volume": 45.17646
  },
  {
    "timestamp": 1774832100000,
    "open": 66183.46,
    "high": 66352.72,
    "low": 66162.19,
    "close": 66280.25,
    "volume": 51.67437
  },
  {
    "timestamp": 1774832400000,
    "open": 66280.24,
    "high": 66566.66,
    "low": 66280.24,
    "close": 66429.25,
    "volume": 49.47086
  },
  {
    "timestamp": 1774832700000,
    "open": 66429.25,
    "high": 66549.54,
    "low": 66367.02,
    "close": 66371.82,
    "volume": 40.9684
  },
  {
    "timestamp": 1774833000000,
    "open": 66371.82,
    "high": 66481.03,
    "low": 66361,
    "close": 66400.2,
    "volume": 61.95133
  },
  {
    "timestamp": 1774833300000,
    "open": 66400.66,
    "high": 66536.14,
    "low": 66328.38,
    "close": 66517.99,
    "volume": 48.46953
  },
  {
    "timestamp": 1774833600000,
    "open": 66518,
    "high": 66535.21,
    "low": 66470.13,
    "close": 66480.56,
    "volume": 34.65965
  },
  {
    "timestamp": 1774833900000,
    "open": 66480.57,
    "high": 66660.32,
    "low": 66480.56,
    "close": 66603.24,
    "volume": 42.50524
  },
  {
    "timestamp": 1774834200000,
    "open": 66603.24,
    "high": 66727.27,
    "low": 66530.33,
    "close": 66703.07,
    "volume": 38.47645
  },
  {
    "timestamp": 1774834500000,
    "open": 66703.06,
    "high": 66731.64,
    "low": 66588.45,
    "close": 66643.85,
    "volume": 34.11792
  },
  {
    "timestamp": 1774834800000,
    "open": 66643.84,
    "high": 66668,
    "low": 66540.1,
    "close": 66668,
    "volume": 91.5559
  },
  {
    "timestamp": 1774835100000,
    "open": 66668,
    "high": 66834.79,
    "low": 66642.83,
    "close": 66764.69,
    "volume": 160.85552
  },
  {
    "timestamp": 1774835400000,
    "open": 66764.69,
    "high": 66764.69,
    "low": 66612.97,
    "close": 66642.24,
    "volume": 43.2368
  },
  {
    "timestamp": 1774835700000,
    "open": 66642.24,
    "high": 66686.61,
    "low": 66599.34,
    "close": 66653.74,
    "volume": 39.60373
  },
  {
    "timestamp": 1774836000000,
    "open": 66653.74,
    "high": 66769.31,
    "low": 66639.6,
    "close": 66642.7,
    "volume": 75.50959
  },
  {
    "timestamp": 1774836300000,
    "open": 66642.69,
    "high": 66860.47,
    "low": 66580.01,
    "close": 66729.6,
    "volume": 56.68202
  },
  {
    "timestamp": 1774836600000,
    "open": 66729.6,
    "high": 66840.59,
    "low": 66682.93,
    "close": 66840.58,
    "volume": 40.85614
  },
  {
    "timestamp": 1774836900000,
    "open": 66840.58,
    "high": 66901.44,
    "low": 66761.96,
    "close": 66771.63,
    "volume": 52.68878
  },
  {
    "timestamp": 1774837200000,
    "open": 66771.62,
    "high": 66771.62,
    "low": 66687.71,
    "close": 66740.31,
    "volume": 25.06762
  },
  {
    "timestamp": 1774837500000,
    "open": 66740.3,
    "high": 66782.36,
    "low": 66692.26,
    "close": 66755.66,
    "volume": 43.25188
  },
  {
    "timestamp": 1774837800000,
    "open": 66755.66,
    "high": 66777.68,
    "low": 66653.3,
    "close": 66654.75,
    "volume": 39.62914
  },
  {
    "timestamp": 1774838100000,
    "open": 66654.76,
    "high": 66689.15,
    "low": 66600,
    "close": 66670.71,
    "volume": 59.39807
  },
  {
    "timestamp": 1774838400000,
    "open": 66670.71,
    "high": 67040.28,
    "low": 66615.16,
    "close": 67038.75,
    "volume": 172.04389
  },
  {
    "timestamp": 1774838700000,
    "open": 67038.75,
    "high": 67450,
    "low": 66992.92,
    "close": 67330.01,
    "volume": 481.41406
  },
  {
    "timestamp": 1774839000000,
    "open": 67330.01,
    "high": 67335.03,
    "low": 67115.08,
    "close": 67161.03,
    "volume": 110.6636
  },
  {
    "timestamp": 1774839300000,
    "open": 67161.03,
    "high": 67184.4,
    "low": 67076.99,
    "close": 67121.01,
    "volume": 63.39738
  },
  {
    "timestamp": 1774839600000,
    "open": 67121.01,
    "high": 67145.75,
    "low": 66977.62,
    "close": 67004.92,
    "volume": 43.39082
  },
  {
    "timestamp": 1774839900000,
    "open": 67004.92,
    "high": 67071.99,
    "low": 66977.62,
    "close": 67051.7,
    "volume": 28.70199
  },
  {
    "timestamp": 1774840200000,
    "open": 67051.7,
    "high": 67069.88,
    "low": 66982.79,
    "close": 67012.46,
    "volume": 37.21034
  },
  {
    "timestamp": 1774840500000,
    "open": 67012.46,
    "high": 67144.15,
    "low": 67001.23,
    "close": 67102.01,
    "volume": 57.27548
  },
  {
    "timestamp": 1774840800000,
    "open": 67102,
    "high": 67294.16,
    "low": 67084.51,
    "close": 67271.13,
    "volume": 59.05343
  },
  {
    "timestamp": 1774841100000,
    "open": 67271.14,
    "high": 67271.14,
    "low": 67171.39,
    "close": 67242.74,
    "volume": 42.2948
  },
  {
    "timestamp": 1774841400000,
    "open": 67242.73,
    "high": 67282.28,
    "low": 67180,
    "close": 67227.33,
    "volume": 43.53602
  },
  {
    "timestamp": 1774841700000,
    "open": 67227.34,
    "high": 67254.84,
    "low": 67150.35,
    "close": 67175.51,
    "volume": 41.61812
  },
  {
    "timestamp": 1774842000000,
    "open": 67175.5,
    "high": 67224.27,
    "low": 67134.23,
    "close": 67196.14,
    "volume": 31.44219
  },
  {
    "timestamp": 1774842300000,
    "open": 67196.14,
    "high": 67206.3,
    "low": 67124.25,
    "close": 67194.09,
    "volume": 28.15127
  },
  {
    "timestamp": 1774842600000,
    "open": 67194.09,
    "high": 67319.33,
    "low": 67157.87,
    "close": 67229.96,
    "volume": 28.86876
  },
  {
    "timestamp": 1774842900000,
    "open": 67229.95,
    "high": 67229.95,
    "low": 67132.09,
    "close": 67173.8,
    "volume": 24.72282
  },
  {
    "timestamp": 1774843200000,
    "open": 67173.8,
    "high": 67265.17,
    "low": 67167.92,
    "close": 67234.44,
    "volume": 47.3434
  },
  {
    "timestamp": 1774843500000,
    "open": 67234.45,
    "high": 67467,
    "low": 67225.67,
    "close": 67410,
    "volume": 80.75612
  },
  {
    "timestamp": 1774843800000,
    "open": 67409.99,
    "high": 67493.46,
    "low": 67373.03,
    "close": 67432.49,
    "volume": 70.65068
  },
  {
    "timestamp": 1774844100000,
    "open": 67432.48,
    "high": 67500,
    "low": 67384.29,
    "close": 67411.67,
    "volume": 77.53779
  },
  {
    "timestamp": 1774844400000,
    "open": 67411.67,
    "high": 67509,
    "low": 67378.67,
    "close": 67393.89,
    "volume": 61.05623
  },
  {
    "timestamp": 1774844700000,
    "open": 67393.89,
    "high": 67650.01,
    "low": 67393.88,
    "close": 67449.19,
    "volume": 165.57374
  },
  {
    "timestamp": 1774845000000,
    "open": 67449.18,
    "high": 67560.96,
    "low": 67429.32,
    "close": 67479.69,
    "volume": 44.73383
  },
  {
    "timestamp": 1774845300000,
    "open": 67479.68,
    "high": 67515.3,
    "low": 67406.46,
    "close": 67515.3,
    "volume": 79.17542
  },
  {
    "timestamp": 1774845600000,
    "open": 67515.3,
    "high": 67515.3,
    "low": 67386.35,
    "close": 67419.76,
    "volume": 56.48735
  },
  {
    "timestamp": 1774845900000,
    "open": 67419.77,
    "high": 67559.42,
    "low": 67419.77,
    "close": 67530.01,
    "volume": 22.65968
  },
  {
    "timestamp": 1774846200000,
    "open": 67530.01,
    "high": 67620.02,
    "low": 67507.59,
    "close": 67612.12,
    "volume": 42.10508
  },
  {
    "timestamp": 1774846500000,
    "open": 67612.12,
    "high": 67647.87,
    "low": 67543.33,
    "close": 67616.29,
    "volume": 61.49299
  },
  {
    "timestamp": 1774846800000,
    "open": 67616.28,
    "high": 67724.36,
    "low": 67581.55,
    "close": 67627.26,
    "volume": 131.18041
  },
  {
    "timestamp": 1774847100000,
    "open": 67627.26,
    "high": 67788,
    "low": 67590.54,
    "close": 67752.94,
    "volume": 49.95714
  },
  {
    "timestamp": 1774847400000,
    "open": 67752.94,
    "high": 67800,
    "low": 67629.93,
    "close": 67646.15,
    "volume": 95.8077
  },
  {
    "timestamp": 1774847700000,
    "open": 67646.14,
    "high": 67728.77,
    "low": 67595.04,
    "close": 67663.77,
    "volume": 46.2713
  },
  {
    "timestamp": 1774848000000,
    "open": 67663.78,
    "high": 67681.66,
    "low": 67632.68,
    "close": 67667.46,
    "volume": 18.2793
  },
  {
    "timestamp": 1774848300000,
    "open": 67667.46,
    "high": 67717.3,
    "low": 67655.98,
    "close": 67665,
    "volume": 31.8755
  },
  {
    "timestamp": 1774848600000,
    "open": 67665,
    "high": 67701.99,
    "low": 67641.08,
    "close": 67648.01,
    "volume": 20.76426
  },
  {
    "timestamp": 1774848900000,
    "open": 67648.04,
    "high": 67656.46,
    "low": 67538.88,
    "close": 67549.7,
    "volume": 40.49947
  },
  {
    "timestamp": 1774849200000,
    "open": 67549.7,
    "high": 67560,
    "low": 67460,
    "close": 67500.01,
    "volume": 58.52437
  },
  {
    "timestamp": 1774849500000,
    "open": 67500.01,
    "high": 67550.12,
    "low": 67442,
    "close": 67542.39,
    "volume": 97.65594
  },
  {
    "timestamp": 1774849800000,
    "open": 67542.39,
    "high": 67561.29,
    "low": 67505,
    "close": 67527.5,
    "volume": 17.7717
  },
  {
    "timestamp": 1774850100000,
    "open": 67527.5,
    "high": 67546.21,
    "low": 67492.46,
    "close": 67492.46,
    "volume": 18.56923
  },
  {
    "timestamp": 1774850400000,
    "open": 67492.46,
    "high": 67585.97,
    "low": 67484.15,
    "close": 67558.89,
    "volume": 40.46301
  },
  {
    "timestamp": 1774850700000,
    "open": 67558.9,
    "high": 67567.86,
    "low": 67490.41,
    "close": 67503.71,
    "volume": 28.16452
  },
  {
    "timestamp": 1774851000000,
    "open": 67503.71,
    "high": 67503.72,
    "low": 67418.58,
    "close": 67447.09,
    "volume": 37.76667
  },
  {
    "timestamp": 1774851300000,
    "open": 67447.08,
    "high": 67462.34,
    "low": 67283.3,
    "close": 67328.01,
    "volume": 87.22414
  },
  {
    "timestamp": 1774851600000,
    "open": 67328.01,
    "high": 67362.25,
    "low": 67303.21,
    "close": 67319.99,
    "volume": 34.61677
  },
  {
    "timestamp": 1774851900000,
    "open": 67320,
    "high": 67372.49,
    "low": 67298.45,
    "close": 67309.99,
    "volume": 141.23867
  },
  {
    "timestamp": 1774852200000,
    "open": 67310,
    "high": 67338.37,
    "low": 67278.53,
    "close": 67316.15,
    "volume": 42.72548
  },
  {
    "timestamp": 1774852500000,
    "open": 67316.16,
    "high": 67351.31,
    "low": 67285.05,
    "close": 67297.24,
    "volume": 114.2334
  },
  {
    "timestamp": 1774852800000,
    "open": 67297.24,
    "high": 67399.46,
    "low": 67297.23,
    "close": 67365.1,
    "volume": 28.30781
  },
  {
    "timestamp": 1774853100000,
    "open": 67365.1,
    "high": 67416.46,
    "low": 67338.13,
    "close": 67381.28,
    "volume": 123.14072
  },
  {
    "timestamp": 1774853400000,
    "open": 67381.27,
    "high": 67428.25,
    "low": 67320.25,
    "close": 67333.88,
    "volume": 28.3383
  },
  {
    "timestamp": 1774853700000,
    "open": 67333.88,
    "high": 67358.88,
    "low": 67296.7,
    "close": 67305.14,
    "volume": 15.56401
  },
  {
    "timestamp": 1774854000000,
    "open": 67305.14,
    "high": 67305.14,
    "low": 67227.88,
    "close": 67272.82,
    "volume": 38.97431
  },
  {
    "timestamp": 1774854300000,
    "open": 67272.82,
    "high": 67420.99,
    "low": 67272.82,
    "close": 67399.04,
    "volume": 31.89762
  },
  {
    "timestamp": 1774854600000,
    "open": 67399.04,
    "high": 67458.38,
    "low": 67370,
    "close": 67383.02,
    "volume": 22.97734
  },
  {
    "timestamp": 1774854900000,
    "open": 67383.02,
    "high": 67437.1,
    "low": 67369.15,
    "close": 67380.43,
    "volume": 40.11958
  },
  {
    "timestamp": 1774855200000,
    "open": 67380.43,
    "high": 67397.35,
    "low": 67300,
    "close": 67307.71,
    "volume": 50.3145
  },
  {
    "timestamp": 1774855500000,
    "open": 67307.71,
    "high": 67353.31,
    "low": 67305.32,
    "close": 67327.99,
    "volume": 22.99824
  },
  {
    "timestamp": 1774855800000,
    "open": 67328,
    "high": 67428.25,
    "low": 67289.31,
    "close": 67335.69,
    "volume": 34.09908
  },
  {
    "timestamp": 1774856100000,
    "open": 67335.7,
    "high": 67416.51,
    "low": 67300,
    "close": 67309.3,
    "volume": 40.52712
  },
  {
    "timestamp": 1774856400000,
    "open": 67309.3,
    "high": 67347.4,
    "low": 67301.99,
    "close": 67318.24,
    "volume": 89.16302
  },
  {
    "timestamp": 1774856700000,
    "open": 67318.24,
    "high": 67451.52,
    "low": 67302.41,
    "close": 67451.52,
    "volume": 67.15855
  },
  {
    "timestamp": 1774857000000,
    "open": 67451.52,
    "high": 67561.29,
    "low": 67414.79,
    "close": 67486,
    "volume": 69.41581
  },
  {
    "timestamp": 1774857300000,
    "open": 67486,
    "high": 67624.39,
    "low": 67485.99,
    "close": 67624.39,
    "volume": 76.82589
  },
  {
    "timestamp": 1774857600000,
    "open": 67624.39,
    "high": 67788.75,
    "low": 67608.49,
    "close": 67778.82,
    "volume": 187.46205
  },
  {
    "timestamp": 1774857900000,
    "open": 67778.82,
    "high": 67907.66,
    "low": 67726.13,
    "close": 67797.02,
    "volume": 233.39815
  },
  {
    "timestamp": 1774858200000,
    "open": 67797.02,
    "high": 67903.92,
    "low": 67778.1,
    "close": 67893.92,
    "volume": 111.6203
  },
  {
    "timestamp": 1774858500000,
    "open": 67893.92,
    "high": 67911.7,
    "low": 67747.68,
    "close": 67900,
    "volume": 397.24505
  },
  {
    "timestamp": 1774858800000,
    "open": 67900,
    "high": 67900,
    "low": 67758.69,
    "close": 67772.87,
    "volume": 41.17058
  },
  {
    "timestamp": 1774859100000,
    "open": 67772.88,
    "high": 67782.15,
    "low": 67737.25,
    "close": 67765.16,
    "volume": 37.41579
  },
  {
    "timestamp": 1774859400000,
    "open": 67765.15,
    "high": 67828.57,
    "low": 67751.68,
    "close": 67754.88,
    "volume": 47.63238
  },
  {
    "timestamp": 1774859700000,
    "open": 67754.88,
    "high": 67946.02,
    "low": 67743,
    "close": 67801.37,
    "volume": 183.36902
  },
  {
    "timestamp": 1774860000000,
    "open": 67801.38,
    "high": 67830.95,
    "low": 67734.8,
    "close": 67761.01,
    "volume": 39.57898
  },
  {
    "timestamp": 1774860300000,
    "open": 67761,
    "high": 67798.55,
    "low": 67689.6,
    "close": 67745.53,
    "volume": 40.67445
  },
  {
    "timestamp": 1774860600000,
    "open": 67745.53,
    "high": 67822.87,
    "low": 67745.53,
    "close": 67763.51,
    "volume": 37.62785
  },
  {
    "timestamp": 1774860900000,
    "open": 67763.51,
    "high": 67763.51,
    "low": 67604.56,
    "close": 67666.44,
    "volume": 371.95716
  },
  {
    "timestamp": 1774861200000,
    "open": 67666.44,
    "high": 67670.56,
    "low": 67597.42,
    "close": 67616.93,
    "volume": 172.34769
  },
  {
    "timestamp": 1774861500000,
    "open": 67616.93,
    "high": 67660,
    "low": 67600.75,
    "close": 67602.71,
    "volume": 48.24015
  },
  {
    "timestamp": 1774861800000,
    "open": 67602.71,
    "high": 67698.62,
    "low": 67580.59,
    "close": 67580.59,
    "volume": 41.23351
  },
  {
    "timestamp": 1774862100000,
    "open": 67580.6,
    "high": 67655.61,
    "low": 67510,
    "close": 67623.94,
    "volume": 65.09677
  },
  {
    "timestamp": 1774862400000,
    "open": 67623.94,
    "high": 67627.3,
    "low": 67517.33,
    "close": 67530.12,
    "volume": 57.35202
  },
  {
    "timestamp": 1774862700000,
    "open": 67530.12,
    "high": 67547,
    "low": 67512.42,
    "close": 67518.37,
    "volume": 18.37998
  },
  {
    "timestamp": 1774863000000,
    "open": 67518.37,
    "high": 67518.37,
    "low": 67463.53,
    "close": 67484.94,
    "volume": 35.29382
  },
  {
    "timestamp": 1774863300000,
    "open": 67484.94,
    "high": 67535.2,
    "low": 67460,
    "close": 67535.19,
    "volume": 40.72668
  },
  {
    "timestamp": 1774863600000,
    "open": 67535.2,
    "high": 67564.72,
    "low": 67467.4,
    "close": 67556.95,
    "volume": 58.78429
  },
  {
    "timestamp": 1774863900000,
    "open": 67556.95,
    "high": 67593.17,
    "low": 67543,
    "close": 67572.3,
    "volume": 28.15563
  },
  {
    "timestamp": 1774864200000,
    "open": 67572.3,
    "high": 67575.53,
    "low": 67540.09,
    "close": 67540.09,
    "volume": 13.17852
  },
  {
    "timestamp": 1774864500000,
    "open": 67540.1,
    "high": 67540.1,
    "low": 67468,
    "close": 67495.46,
    "volume": 28.65367
  },
  {
    "timestamp": 1774864800000,
    "open": 67495.46,
    "high": 67502.95,
    "low": 67436.37,
    "close": 67471.4,
    "volume": 46.53413
  },
  {
    "timestamp": 1774865100000,
    "open": 67471.4,
    "high": 67477,
    "low": 67455.45,
    "close": 67468.44,
    "volume": 13.91127
  },
  {
    "timestamp": 1774865400000,
    "open": 67468.44,
    "high": 67478,
    "low": 67402,
    "close": 67440.51,
    "volume": 32.37798
  },
  {
    "timestamp": 1774865700000,
    "open": 67440.51,
    "high": 67480,
    "low": 67421.13,
    "close": 67476.99,
    "volume": 18.20497
  },
  {
    "timestamp": 1774866000000,
    "open": 67477,
    "high": 67492.91,
    "low": 67430.32,
    "close": 67430.33,
    "volume": 11.19521
  },
  {
    "timestamp": 1774866300000,
    "open": 67430.33,
    "high": 67452.3,
    "low": 67418.98,
    "close": 67424.01,
    "volume": 12.74843
  },
  {
    "timestamp": 1774866600000,
    "open": 67424.01,
    "high": 67437.52,
    "low": 67407.96,
    "close": 67413.01,
    "volume": 11.43645
  },
  {
    "timestamp": 1774866900000,
    "open": 67413.01,
    "high": 67415.01,
    "low": 67360.41,
    "close": 67403.99,
    "volume": 43.88763
  },
  {
    "timestamp": 1774867200000,
    "open": 67404,
    "high": 67433.32,
    "low": 67385.38,
    "close": 67433.32,
    "volume": 22.21118
  },
  {
    "timestamp": 1774867500000,
    "open": 67433.32,
    "high": 67479.84,
    "low": 67423.8,
    "close": 67476.34,
    "volume": 11.06872
  },
  {
    "timestamp": 1774867800000,
    "open": 67476.34,
    "high": 67518.37,
    "low": 67468.93,
    "close": 67497.99,
    "volume": 22.3677
  },
  {
    "timestamp": 1774868100000,
    "open": 67497.99,
    "high": 67514.01,
    "low": 67482.32,
    "close": 67488.53,
    "volume": 9.69299
  },
  {
    "timestamp": 1774868400000,
    "open": 67488.88,
    "high": 67560.02,
    "low": 67488.88,
    "close": 67512.7,
    "volume": 31.44112
  },
  {
    "timestamp": 1774868700000,
    "open": 67512.7,
    "high": 67579.99,
    "low": 67512.69,
    "close": 67562.79,
    "volume": 16.85772
  },
  {
    "timestamp": 1774869000000,
    "open": 67562.78,
    "high": 67585.97,
    "low": 67533.5,
    "close": 67585.96,
    "volume": 21.16691
  },
  {
    "timestamp": 1774869300000,
    "open": 67585.96,
    "high": 67587.44,
    "low": 67546.43,
    "close": 67553.57,
    "volume": 21.49978
  },
  {
    "timestamp": 1774869600000,
    "open": 67553.56,
    "high": 67634.92,
    "low": 67542.16,
    "close": 67604,
    "volume": 22.62078
  },
  {
    "timestamp": 1774869900000,
    "open": 67604,
    "high": 68042.3,
    "low": 67596,
    "close": 67690.49,
    "volume": 357.89247
  },
  {
    "timestamp": 1774870200000,
    "open": 67690.5,
    "high": 67748.57,
    "low": 67584.6,
    "close": 67594.25,
    "volume": 79.78148
  },
  {
    "timestamp": 1774870500000,
    "open": 67594.24,
    "high": 67673.02,
    "low": 67511.01,
    "close": 67539.5,
    "volume": 90.70979
  },
  {
    "timestamp": 1774870800000,
    "open": 67539.5,
    "high": 67616.46,
    "low": 67519.44,
    "close": 67596.01,
    "volume": 52.50527
  },
  {
    "timestamp": 1774871100000,
    "open": 67596.01,
    "high": 67739,
    "low": 67587.51,
    "close": 67703.61,
    "volume": 46.13681
  },
  {
    "timestamp": 1774871400000,
    "open": 67703.61,
    "high": 67736.44,
    "low": 67639.03,
    "close": 67659.99,
    "volume": 24.35998
  },
  {
    "timestamp": 1774871700000,
    "open": 67660,
    "high": 67680.45,
    "low": 67614.48,
    "close": 67680.45,
    "volume": 25.88997
  },
  {
    "timestamp": 1774872000000,
    "open": 67680.44,
    "high": 67788.75,
    "low": 67666.17,
    "close": 67788.74,
    "volume": 36.18058
  },
  {
    "timestamp": 1774872300000,
    "open": 67788.75,
    "high": 67841.98,
    "low": 67769.05,
    "close": 67797.45,
    "volume": 47.66221
  },
  {
    "timestamp": 1774872600000,
    "open": 67797.45,
    "high": 67873.89,
    "low": 67797.44,
    "close": 67850.19,
    "volume": 47.24692
  },
  {
    "timestamp": 1774872900000,
    "open": 67850.19,
    "high": 67920,
    "low": 67802.5,
    "close": 67900.11,
    "volume": 88.86789
  },
  {
    "timestamp": 1774873200000,
    "open": 67900.11,
    "high": 67979.93,
    "low": 67870,
    "close": 67892.79,
    "volume": 124.2238
  },
  {
    "timestamp": 1774873500000,
    "open": 67892.8,
    "high": 67912,
    "low": 67825.24,
    "close": 67861.24,
    "volume": 54.75631
  },
  {
    "timestamp": 1774873800000,
    "open": 67861.24,
    "high": 67965.72,
    "low": 67861.23,
    "close": 67925.79,
    "volume": 51.33856
  },
  {
    "timestamp": 1774874100000,
    "open": 67925.8,
    "high": 67964.78,
    "low": 67850,
    "close": 67858.97,
    "volume": 49.29062
  },
  {
    "timestamp": 1774874400000,
    "open": 67858.97,
    "high": 67891.63,
    "low": 67820.48,
    "close": 67883.35,
    "volume": 38.97062
  },
  {
    "timestamp": 1774874700000,
    "open": 67883.36,
    "high": 67950,
    "low": 67844.52,
    "close": 67868.69,
    "volume": 31.02968
  },
  {
    "timestamp": 1774875000000,
    "open": 67868.69,
    "high": 67906.86,
    "low": 67862.4,
    "close": 67879.82,
    "volume": 23.79068
  },
  {
    "timestamp": 1774875300000,
    "open": 67879.82,
    "high": 67932.39,
    "low": 67865.86,
    "close": 67899.59,
    "volume": 34.29662
  },
  {
    "timestamp": 1774875600000,
    "open": 67899.59,
    "high": 67926,
    "low": 67841.99,
    "close": 67911.23,
    "volume": 48.85634
  },
  {
    "timestamp": 1774875900000,
    "open": 67911.23,
    "high": 67968,
    "low": 67854,
    "close": 67884.7,
    "volume": 36.48723
  },
  {
    "timestamp": 1774876200000,
    "open": 67884.7,
    "high": 67968.99,
    "low": 67879.14,
    "close": 67915.01,
    "volume": 35.75324
  },
  {
    "timestamp": 1774876500000,
    "open": 67915.01,
    "high": 67959.26,
    "low": 67880,
    "close": 67949.38,
    "volume": 25.49077
  },
  {
    "timestamp": 1774876800000,
    "open": 67949.38,
    "high": 68169.65,
    "low": 67921.7,
    "close": 68030.02,
    "volume": 403.07656
  },
  {
    "timestamp": 1774877100000,
    "open": 68030.02,
    "high": 68030.02,
    "low": 67878.85,
    "close": 67878.85,
    "volume": 96.98151
  },
  {
    "timestamp": 1774877400000,
    "open": 67878.85,
    "high": 68042,
    "low": 67777.77,
    "close": 67911.6,
    "volume": 159.01508
  },
  {
    "timestamp": 1774877700000,
    "open": 67911.6,
    "high": 67986,
    "low": 67855.04,
    "close": 67880.99,
    "volume": 109.47271
  },
  {
    "timestamp": 1774878000000,
    "open": 67880.04,
    "high": 67880.04,
    "low": 67706.52,
    "close": 67714.36,
    "volume": 133.72321
  },
  {
    "timestamp": 1774878300000,
    "open": 67714.36,
    "high": 67838.29,
    "low": 67627.43,
    "close": 67627.43,
    "volume": 74.32179
  },
  {
    "timestamp": 1774878600000,
    "open": 67627.44,
    "high": 67777.98,
    "low": 67627.44,
    "close": 67684.5,
    "volume": 57.60457
  },
  {
    "timestamp": 1774878900000,
    "open": 67684.49,
    "high": 67684.49,
    "low": 67428.57,
    "close": 67529.52,
    "volume": 199.20876
  },
  {
    "timestamp": 1774879200000,
    "open": 67529.52,
    "high": 67629.25,
    "low": 67490.56,
    "close": 67604.41,
    "volume": 66.4035
  },
  {
    "timestamp": 1774879500000,
    "open": 67604.41,
    "high": 67631.37,
    "low": 67468.75,
    "close": 67631.36,
    "volume": 73.3776
  },
  {
    "timestamp": 1774879800000,
    "open": 67631.36,
    "high": 67753.78,
    "low": 67586.8,
    "close": 67678.92,
    "volume": 66.10818
  },
  {
    "timestamp": 1774880100000,
    "open": 67678.92,
    "high": 67706.59,
    "low": 67372.12,
    "close": 67421.87,
    "volume": 110.23118
  },
  {
    "timestamp": 1774880400000,
    "open": 67421.87,
    "high": 67500,
    "low": 67380.16,
    "close": 67478,
    "volume": 43.56824
  },
  {
    "timestamp": 1774880700000,
    "open": 67478,
    "high": 67490,
    "low": 67242.5,
    "close": 67313.59,
    "volume": 112.94191
  },
  {
    "timestamp": 1774881000000,
    "open": 67313.59,
    "high": 67404.48,
    "low": 67297.01,
    "close": 67350.51,
    "volume": 70.54487
  },
  {
    "timestamp": 1774881300000,
    "open": 67350.5,
    "high": 67375.3,
    "low": 67130.75,
    "close": 67321.29,
    "volume": 186.50491
  },
  {
    "timestamp": 1774881600000,
    "open": 67321.3,
    "high": 67364.06,
    "low": 67113.2,
    "close": 67123.93,
    "volume": 101.36892
  },
  {
    "timestamp": 1774881900000,
    "open": 67123.93,
    "high": 67332.32,
    "low": 67088.73,
    "close": 67234.26,
    "volume": 79.44045
  },
  {
    "timestamp": 1774882200000,
    "open": 67234.26,
    "high": 67558.7,
    "low": 67216.05,
    "close": 67529.51,
    "volume": 157.71484
  },
  {
    "timestamp": 1774882500000,
    "open": 67529.51,
    "high": 67864.49,
    "low": 67504.05,
    "close": 67799.54,
    "volume": 137.36737
  },
  {
    "timestamp": 1774882800000,
    "open": 67799.54,
    "high": 67869.98,
    "low": 67738.84,
    "close": 67803.23,
    "volume": 146.19722
  },
  {
    "timestamp": 1774883100000,
    "open": 67803.23,
    "high": 67878.87,
    "low": 67563.31,
    "close": 67608.5,
    "volume": 103.5106
  },
  {
    "timestamp": 1774883400000,
    "open": 67608.5,
    "high": 67701,
    "low": 67554.51,
    "close": 67561.67,
    "volume": 62.476
  },
  {
    "timestamp": 1774883700000,
    "open": 67561.67,
    "high": 67581.6,
    "low": 67428.24,
    "close": 67452.63,
    "volume": 108.05376
  },
  {
    "timestamp": 1774884000000,
    "open": 67452.63,
    "high": 67485.44,
    "low": 67407.63,
    "close": 67436.78,
    "volume": 38.21999
  },
  {
    "timestamp": 1774884300000,
    "open": 67436.79,
    "high": 67606.31,
    "low": 67436.79,
    "close": 67522.8,
    "volume": 102.29137
  },
  {
    "timestamp": 1774884600000,
    "open": 67522.8,
    "high": 67780.9,
    "low": 67462.57,
    "close": 67763.67,
    "volume": 113.40564
  },
  {
    "timestamp": 1774884900000,
    "open": 67763.67,
    "high": 67896.89,
    "low": 67759.78,
    "close": 67818.96,
    "volume": 63.10055
  },
  {
    "timestamp": 1774885200000,
    "open": 67818.95,
    "high": 67861.14,
    "low": 67732.83,
    "close": 67751.6,
    "volume": 54.92049
  },
  {
    "timestamp": 1774885500000,
    "open": 67751.6,
    "high": 67769.52,
    "low": 67685.48,
    "close": 67695.33,
    "volume": 75.23451
  },
  {
    "timestamp": 1774885800000,
    "open": 67695.33,
    "high": 67788.75,
    "low": 67689.6,
    "close": 67732.02,
    "volume": 41.40927
  },
  {
    "timestamp": 1774886100000,
    "open": 67732.02,
    "high": 67732.02,
    "low": 67598.38,
    "close": 67629.4,
    "volume": 55.88533
  },
  {
    "timestamp": 1774886400000,
    "open": 67629.4,
    "high": 67641.65,
    "low": 67415.38,
    "close": 67426.25,
    "volume": 49.44942
  },
  {
    "timestamp": 1774886700000,
    "open": 67426.59,
    "high": 67450.28,
    "low": 67339.59,
    "close": 67432.15,
    "volume": 65.36913
  },
  {
    "timestamp": 1774887000000,
    "open": 67432.14,
    "high": 67475.04,
    "low": 67427.95,
    "close": 67441.4,
    "volume": 58.91172
  },
  {
    "timestamp": 1774887300000,
    "open": 67441.4,
    "high": 67475.04,
    "low": 67372.66,
    "close": 67394.45,
    "volume": 47.7056
  },
  {
    "timestamp": 1774887600000,
    "open": 67394.44,
    "high": 67410.03,
    "low": 67287.96,
    "close": 67340.22,
    "volume": 64.40638
  },
  {
    "timestamp": 1774887900000,
    "open": 67340.22,
    "high": 67386.2,
    "low": 67321.52,
    "close": 67351.12,
    "volume": 35.27915
  },
  {
    "timestamp": 1774888200000,
    "open": 67351.12,
    "high": 67438.35,
    "low": 67311.66,
    "close": 67396.08,
    "volume": 94.4361
  },
  {
    "timestamp": 1774888500000,
    "open": 67396.08,
    "high": 67508.13,
    "low": 67396.07,
    "close": 67439.81,
    "volume": 72.02658
  },
  {
    "timestamp": 1774888800000,
    "open": 67439.81,
    "high": 67439.81,
    "low": 67329.63,
    "close": 67372.33,
    "volume": 33.36542
  },
  {
    "timestamp": 1774889100000,
    "open": 67372.33,
    "high": 67441.88,
    "low": 67324.15,
    "close": 67348.14,
    "volume": 23.70012
  },
  {
    "timestamp": 1774889400000,
    "open": 67348.14,
    "high": 67382.46,
    "low": 67250.49,
    "close": 67250.49,
    "volume": 50.51408
  },
  {
    "timestamp": 1774889700000,
    "open": 67250.5,
    "high": 67368.1,
    "low": 67222,
    "close": 67368.1,
    "volume": 65.10423
  },
  {
    "timestamp": 1774890000000,
    "open": 67368.1,
    "high": 67465.2,
    "low": 67267.61,
    "close": 67270.43,
    "volume": 44.60804
  },
  {
    "timestamp": 1774890300000,
    "open": 67270.43,
    "high": 67346.54,
    "low": 67228,
    "close": 67295.33,
    "volume": 34.15138
  },
  {
    "timestamp": 1774890600000,
    "open": 67295.32,
    "high": 67297.83,
    "low": 67157.18,
    "close": 67185.24,
    "volume": 92.89062
  },
  {
    "timestamp": 1774890900000,
    "open": 67185.24,
    "high": 67188.94,
    "low": 67083.64,
    "close": 67123.8,
    "volume": 125.04106
  },
  {
    "timestamp": 1774891200000,
    "open": 67123.8,
    "high": 67154.07,
    "low": 66806.09,
    "close": 66846.03,
    "volume": 205.6374
  },
  {
    "timestamp": 1774891500000,
    "open": 66846.03,
    "high": 66846.03,
    "low": 66650,
    "close": 66805.26,
    "volume": 132.27163
  },
  {
    "timestamp": 1774891800000,
    "open": 66805.26,
    "high": 66910.03,
    "low": 66762,
    "close": 66860.81,
    "volume": 98.39846
  },
  {
    "timestamp": 1774892100000,
    "open": 66860.81,
    "high": 66952,
    "low": 66795.46,
    "close": 66922.12,
    "volume": 33.51381
  },
  {
    "timestamp": 1774892400000,
    "open": 66922.13,
    "high": 66958.94,
    "low": 66879.04,
    "close": 66958.03,
    "volume": 26.88981
  },
  {
    "timestamp": 1774892700000,
    "open": 66958.04,
    "high": 66990.67,
    "low": 66822.05,
    "close": 66887.51,
    "volume": 50.27857
  },
  {
    "timestamp": 1774893000000,
    "open": 66887.5,
    "high": 66898,
    "low": 66797.09,
    "close": 66801.24,
    "volume": 40.73158
  },
  {
    "timestamp": 1774893300000,
    "open": 66801.24,
    "high": 66860.62,
    "low": 66782.13,
    "close": 66828.02,
    "volume": 33.30137
  },
  {
    "timestamp": 1774893600000,
    "open": 66828.02,
    "high": 66929.18,
    "low": 66814.63,
    "close": 66836.44,
    "volume": 27.06117
  },
  {
    "timestamp": 1774893900000,
    "open": 66836.44,
    "high": 66857.01,
    "low": 66711.49,
    "close": 66725.87,
    "volume": 40.58355
  },
  {
    "timestamp": 1774894200000,
    "open": 66725.88,
    "high": 66843.08,
    "low": 66705.27,
    "close": 66825.05,
    "volume": 36.12737
  },
  {
    "timestamp": 1774894500000,
    "open": 66825.05,
    "high": 66831.73,
    "low": 66753.63,
    "close": 66783.21,
    "volume": 34.6028
  },
  {
    "timestamp": 1774894800000,
    "open": 66783.2,
    "high": 66856.69,
    "low": 66615.38,
    "close": 66685.83,
    "volume": 60.06396
  },
  {
    "timestamp": 1774895100000,
    "open": 66685.83,
    "high": 66717.28,
    "low": 66581.07,
    "close": 66700.12,
    "volume": 67.34832
  },
  {
    "timestamp": 1774895400000,
    "open": 66700.12,
    "high": 66797.38,
    "low": 66576.47,
    "close": 66762.62,
    "volume": 65.39761
  },
  {
    "timestamp": 1774895700000,
    "open": 66762.62,
    "high": 66819.65,
    "low": 66700.36,
    "close": 66700.37,
    "volume": 22.79793
  },
  {
    "timestamp": 1774896000000,
    "open": 66700.36,
    "high": 66751.84,
    "low": 66683.77,
    "close": 66739.53,
    "volume": 14.66337
  },
  {
    "timestamp": 1774896300000,
    "open": 66739.53,
    "high": 66787.03,
    "low": 66642.21,
    "close": 66642.21,
    "volume": 27.89761
  },
  {
    "timestamp": 1774896600000,
    "open": 66642.21,
    "high": 66642.21,
    "low": 66508.25,
    "close": 66612.7,
    "volume": 47.53153
  },
  {
    "timestamp": 1774896900000,
    "open": 66612.7,
    "high": 66659.26,
    "low": 66547.23,
    "close": 66653.46,
    "volume": 54.04216
  },
  {
    "timestamp": 1774897200000,
    "open": 66653.45,
    "high": 66664.57,
    "low": 66551.2,
    "close": 66602.96,
    "volume": 22.53433
  },
  {
    "timestamp": 1774897500000,
    "open": 66602.95,
    "high": 66604.82,
    "low": 66373.91,
    "close": 66440.4,
    "volume": 117.41711
  },
  {
    "timestamp": 1774897800000,
    "open": 66440.4,
    "high": 66443.18,
    "low": 66300,
    "close": 66425.62,
    "volume": 61.99963
  },
  {
    "timestamp": 1774898100000,
    "open": 66425.62,
    "high": 66457.99,
    "low": 66370.72,
    "close": 66389.18,
    "volume": 35.40656
  },
  {
    "timestamp": 1774898400000,
    "open": 66389.19,
    "high": 66436,
    "low": 66233.13,
    "close": 66246.72,
    "volume": 57.70378
  },
  {
    "timestamp": 1774898700000,
    "open": 66246.72,
    "high": 66376.8,
    "low": 66246.71,
    "close": 66310.09,
    "volume": 40.54706
  },
  {
    "timestamp": 1774899000000,
    "open": 66310.1,
    "high": 66403.55,
    "low": 66285.9,
    "close": 66346.76,
    "volume": 41.01824
  },
  {
    "timestamp": 1774899300000,
    "open": 66346.76,
    "high": 66397.23,
    "low": 66311.77,
    "close": 66338.3,
    "volume": 39.72852
  },
  {
    "timestamp": 1774899600000,
    "open": 66338.3,
    "high": 66370.98,
    "low": 66243.37,
    "close": 66339,
    "volume": 28.55919
  },
  {
    "timestamp": 1774899900000,
    "open": 66339,
    "high": 66453.45,
    "low": 66292.11,
    "close": 66453.44,
    "volume": 33.96463
  },
  {
    "timestamp": 1774900200000,
    "open": 66453.45,
    "high": 66518.91,
    "low": 66430.25,
    "close": 66518.01,
    "volume": 44.37814
  },
  {
    "timestamp": 1774900500000,
    "open": 66518.01,
    "high": 66573.54,
    "low": 66465.93,
    "close": 66550.05,
    "volume": 74.64067
  },
  {
    "timestamp": 1774900800000,
    "open": 66550.06,
    "high": 66606.83,
    "low": 66523.75,
    "close": 66553.83,
    "volume": 45.82521
  },
  {
    "timestamp": 1774901100000,
    "open": 66553.84,
    "high": 66691.48,
    "low": 66553.84,
    "close": 66637.81,
    "volume": 36.72565
  },
  {
    "timestamp": 1774901400000,
    "open": 66637.81,
    "high": 66677.34,
    "low": 66598.07,
    "close": 66598.34,
    "volume": 25.73386
  },
  {
    "timestamp": 1774901700000,
    "open": 66598.34,
    "high": 66627.53,
    "low": 66553.92,
    "close": 66600.57,
    "volume": 34.99076
  },
  {
    "timestamp": 1774902000000,
    "open": 66600.57,
    "high": 66672.96,
    "low": 66600.57,
    "close": 66666.29,
    "volume": 26.33746
  },
  {
    "timestamp": 1774902300000,
    "open": 66666.28,
    "high": 66666.29,
    "low": 66637.66,
    "close": 66655.94,
    "volume": 28.19971
  },
  {
    "timestamp": 1774902600000,
    "open": 66655.95,
    "high": 66671.73,
    "low": 66568.1,
    "close": 66592.79,
    "volume": 20.86357
  },
  {
    "timestamp": 1774902900000,
    "open": 66592.79,
    "high": 66660.75,
    "low": 66554.01,
    "close": 66660.74,
    "volume": 20.47996
  },
  {
    "timestamp": 1774903200000,
    "open": 66660.74,
    "high": 66682.82,
    "low": 66643.32,
    "close": 66664.66,
    "volume": 22.01366
  },
  {
    "timestamp": 1774903500000,
    "open": 66664.66,
    "high": 66674.9,
    "low": 66610.02,
    "close": 66629.88,
    "volume": 22.43204
  },
  {
    "timestamp": 1774903800000,
    "open": 66629.88,
    "high": 66662.18,
    "low": 66621.97,
    "close": 66662.17,
    "volume": 16.05769
  },
  {
    "timestamp": 1774904100000,
    "open": 66662.18,
    "high": 66669.51,
    "low": 66644.85,
    "close": 66651.4,
    "volume": 24.95245
  },
  {
    "timestamp": 1774904400000,
    "open": 66651.41,
    "high": 66659.04,
    "low": 66607.39,
    "close": 66607.4,
    "volume": 26.71841
  },
  {
    "timestamp": 1774904700000,
    "open": 66607.4,
    "high": 66730.94,
    "low": 66587.32,
    "close": 66716.8,
    "volume": 61.45595
  },
  {
    "timestamp": 1774905000000,
    "open": 66716.79,
    "high": 66797.38,
    "low": 66714.74,
    "close": 66786.13,
    "volume": 55.98223
  },
  {
    "timestamp": 1774905300000,
    "open": 66786.13,
    "high": 66870.33,
    "low": 66771.61,
    "close": 66859.52,
    "volume": 67.97556
  },
  {
    "timestamp": 1774905600000,
    "open": 66859.52,
    "high": 66994.17,
    "low": 66859.51,
    "close": 66972.96,
    "volume": 101.90153
  },
  {
    "timestamp": 1774905900000,
    "open": 66972.96,
    "high": 66972.96,
    "low": 66850,
    "close": 66860.47,
    "volume": 23.93506
  },
  {
    "timestamp": 1774906200000,
    "open": 66860.47,
    "high": 66895.58,
    "low": 66820.64,
    "close": 66880.71,
    "volume": 28.00941
  },
  {
    "timestamp": 1774906500000,
    "open": 66880.71,
    "high": 66948.98,
    "low": 66860.46,
    "close": 66921.07,
    "volume": 17.33736
  },
  {
    "timestamp": 1774906800000,
    "open": 66921.07,
    "high": 66991.93,
    "low": 66861.71,
    "close": 66929.46,
    "volume": 43.82685
  },
  {
    "timestamp": 1774907100000,
    "open": 66929.46,
    "high": 66945.08,
    "low": 66860.47,
    "close": 66895.12,
    "volume": 22.23377
  },
  {
    "timestamp": 1774907400000,
    "open": 66895.12,
    "high": 66927.56,
    "low": 66862.46,
    "close": 66862.46,
    "volume": 12.71637
  },
  {
    "timestamp": 1774907700000,
    "open": 66862.45,
    "high": 66862.46,
    "low": 66799.58,
    "close": 66809.3,
    "volume": 19.3295
  },
  {
    "timestamp": 1774908000000,
    "open": 66809.3,
    "high": 66988,
    "low": 66809.3,
    "close": 66982.95,
    "volume": 18.92656
  },
  {
    "timestamp": 1774908300000,
    "open": 66982.96,
    "high": 66989.1,
    "low": 66730.17,
    "close": 66739.33,
    "volume": 33.14349
  },
  {
    "timestamp": 1774908600000,
    "open": 66739.33,
    "high": 66797.38,
    "low": 66702.34,
    "close": 66771.62,
    "volume": 18.59187
  },
  {
    "timestamp": 1774908900000,
    "open": 66771.62,
    "high": 66820.54,
    "low": 66728.34,
    "close": 66790.67,
    "volume": 11.74351
  },
  {
    "timestamp": 1774909200000,
    "open": 66790.66,
    "high": 66852,
    "low": 66780.46,
    "close": 66852,
    "volume": 9.84145
  },
  {
    "timestamp": 1774909500000,
    "open": 66852,
    "high": 66893.62,
    "low": 66801.13,
    "close": 66820.25,
    "volume": 10.77406
  },
  {
    "timestamp": 1774909800000,
    "open": 66820.26,
    "high": 66820.26,
    "low": 66743.86,
    "close": 66804.34,
    "volume": 6.09903
  },
  {
    "timestamp": 1774910100000,
    "open": 66804.34,
    "high": 66826.74,
    "low": 66789.22,
    "close": 66801.62,
    "volume": 6.46833
  },
  {
    "timestamp": 1774910400000,
    "open": 66801.62,
    "high": 66856.42,
    "low": 66801.62,
    "close": 66831.69,
    "volume": 7.50218
  },
  {
    "timestamp": 1774910700000,
    "open": 66831.69,
    "high": 66840.95,
    "low": 66683.72,
    "close": 66736.91,
    "volume": 24.83677
  },
  {
    "timestamp": 1774911000000,
    "open": 66736.91,
    "high": 66766.65,
    "low": 66721.29,
    "close": 66762.91,
    "volume": 11.58484
  },
  {
    "timestamp": 1774911300000,
    "open": 66762.92,
    "high": 66797.38,
    "low": 66762.92,
    "close": 66784.98,
    "volume": 9.99107
  },
  {
    "timestamp": 1774911600000,
    "open": 66784.97,
    "high": 66784.97,
    "low": 66459.9,
    "close": 66492.19,
    "volume": 64.01963
  },
  {
    "timestamp": 1774911900000,
    "open": 66492.19,
    "high": 66560.39,
    "low": 66419.79,
    "close": 66463.89,
    "volume": 77.00915
  },
  {
    "timestamp": 1774912200000,
    "open": 66463.88,
    "high": 66550.32,
    "low": 66450.28,
    "close": 66550.32,
    "volume": 116.71825
  },
  {
    "timestamp": 1774912500000,
    "open": 66550.32,
    "high": 66647.99,
    "low": 66522.97,
    "close": 66591.64,
    "volume": 47.50701
  },
  {
    "timestamp": 1774912800000,
    "open": 66591.64,
    "high": 66670.99,
    "low": 66591.63,
    "close": 66667.16,
    "volume": 46.29964
  },
  {
    "timestamp": 1774913100000,
    "open": 66667.17,
    "high": 66738.21,
    "low": 66639.16,
    "close": 66707.57,
    "volume": 35.76635
  },
  {
    "timestamp": 1774913400000,
    "open": 66707.57,
    "high": 66750.57,
    "low": 66688,
    "close": 66750.56,
    "volume": 28.9853
  },
  {
    "timestamp": 1774913700000,
    "open": 66750.57,
    "high": 66778.29,
    "low": 66696.31,
    "close": 66696.32,
    "volume": 118.4281
  },
  {
    "timestamp": 1774914000000,
    "open": 66696.32,
    "high": 66773.16,
    "low": 66663.23,
    "close": 66765.9,
    "volume": 42.8467
  },
  {
    "timestamp": 1774914300000,
    "open": 66765.89,
    "high": 66765.89,
    "low": 66720.37,
    "close": 66734.88,
    "volume": 49.66619
  },
  {
    "timestamp": 1774914600000,
    "open": 66734.88,
    "high": 66771.61,
    "low": 66734.88,
    "close": 66750.09,
    "volume": 44.09535
  },
  {
    "timestamp": 1774914900000,
    "open": 66750.1,
    "high": 66797.38,
    "low": 66732.3,
    "close": 66797.37,
    "volume": 26.90023
  },
  {
    "timestamp": 1774915200000,
    "open": 66797.38,
    "high": 66821.35,
    "low": 66707.26,
    "close": 66817.9,
    "volume": 99.78047
  },
  {
    "timestamp": 1774915500000,
    "open": 66817.89,
    "high": 66817.89,
    "low": 66687.98,
    "close": 66713.85,
    "volume": 15.12117
  },
  {
    "timestamp": 1774915800000,
    "open": 66713.85,
    "high": 66713.9,
    "low": 66570.67,
    "close": 66653.19,
    "volume": 20.71606
  },
  {
    "timestamp": 1774916100000,
    "open": 66653.19,
    "high": 66674.73,
    "low": 66544.51,
    "close": 66614.08,
    "volume": 26.63281
  },
  {
    "timestamp": 1774916400000,
    "open": 66615.69,
    "high": 66710.13,
    "low": 66578.06,
    "close": 66707.26,
    "volume": 43.32832
  },
  {
    "timestamp": 1774916700000,
    "open": 66707.27,
    "high": 66831.54,
    "low": 66696.55,
    "close": 66815.48,
    "volume": 28.00447
  },
  {
    "timestamp": 1774917000000,
    "open": 66815.48,
    "high": 66846.77,
    "low": 66771.62,
    "close": 66800.5,
    "volume": 31.23855
  },
  {
    "timestamp": 1774917300000,
    "open": 66800.51,
    "high": 66954.65,
    "low": 66797.81,
    "close": 66923.01,
    "volume": 83.30722
  },
  {
    "timestamp": 1774917600000,
    "open": 66923.02,
    "high": 66947.14,
    "low": 66796.33,
    "close": 66942.98,
    "volume": 44.16758
  },
  {
    "timestamp": 1774917900000,
    "open": 66942.99,
    "high": 67303.33,
    "low": 66942.99,
    "close": 67263.09,
    "volume": 158.79368
  },
  {
    "timestamp": 1774918200000,
    "open": 67263.09,
    "high": 67264,
    "low": 67010.49,
    "close": 67134.39,
    "volume": 74.62704
  },
  {
    "timestamp": 1774918500000,
    "open": 67134.38,
    "high": 67208.75,
    "low": 67083.54,
    "close": 67208.75,
    "volume": 33.22792
  },
  {
    "timestamp": 1774918800000,
    "open": 67208.74,
    "high": 67288,
    "low": 67136,
    "close": 67142.2,
    "volume": 33.16904
  },
  {
    "timestamp": 1774919100000,
    "open": 67142.2,
    "high": 67157.34,
    "low": 67050,
    "close": 67096.6,
    "volume": 32.21629
  },
  {
    "timestamp": 1774919400000,
    "open": 67096.6,
    "high": 67270,
    "low": 67096.59,
    "close": 67234.97,
    "volume": 35.35412
  },
  {
    "timestamp": 1774919700000,
    "open": 67234.97,
    "high": 67436.36,
    "low": 67234.97,
    "close": 67418.3,
    "volume": 52.66622
  },
  {
    "timestamp": 1774920000000,
    "open": 67418.3,
    "high": 67817.37,
    "low": 67384.74,
    "close": 67805.45,
    "volume": 179.27664
  },
  {
    "timestamp": 1774920300000,
    "open": 67805.45,
    "high": 67881.96,
    "low": 67665.12,
    "close": 67775.48,
    "volume": 127.59053
  },
  {
    "timestamp": 1774920600000,
    "open": 67775.48,
    "high": 68408.37,
    "low": 67737.56,
    "close": 68338.18,
    "volume": 423.996
  },
  {
    "timestamp": 1774920900000,
    "open": 68338.18,
    "high": 68382.51,
    "low": 68100.04,
    "close": 68189.92,
    "volume": 308.34477
  },
  {
    "timestamp": 1774921200000,
    "open": 68189.92,
    "high": 68208.39,
    "low": 67902.1,
    "close": 67933.31,
    "volume": 107.09475
  },
  {
    "timestamp": 1774921500000,
    "open": 67933.31,
    "high": 67985.75,
    "low": 67818.18,
    "close": 67906.25,
    "volume": 53.20434
  },
  {
    "timestamp": 1774921800000,
    "open": 67906.19,
    "high": 68005.91,
    "low": 67839.99,
    "close": 67957.99,
    "volume": 51.95934
  },
  {
    "timestamp": 1774922100000,
    "open": 67958,
    "high": 68050.94,
    "low": 67938.54,
    "close": 67938.54,
    "volume": 53.18344
  },
  {
    "timestamp": 1774922400000,
    "open": 67938.05,
    "high": 67972.59,
    "low": 67775.18,
    "close": 67880.65,
    "volume": 72.2576
  },
  {
    "timestamp": 1774922700000,
    "open": 67880.64,
    "high": 67986.41,
    "low": 67873.21,
    "close": 67882.4,
    "volume": 31.52491
  },
  {
    "timestamp": 1774923000000,
    "open": 67882.4,
    "high": 67933.63,
    "low": 67871.27,
    "close": 67916.59,
    "volume": 25.78932
  },
  {
    "timestamp": 1774923300000,
    "open": 67916.6,
    "high": 68096.87,
    "low": 67916.59,
    "close": 68029.85,
    "volume": 55.32523
  },
  {
    "timestamp": 1774923600000,
    "open": 68029.84,
    "high": 68054,
    "low": 68000,
    "close": 68054,
    "volume": 47.64878
  },
  {
    "timestamp": 1774923900000,
    "open": 68054,
    "high": 68067.91,
    "low": 67988,
    "close": 68049.04,
    "volume": 48.09962
  },
  {
    "timestamp": 1774924200000,
    "open": 68049.05,
    "high": 68064.29,
    "low": 67845.42,
    "close": 67933.13,
    "volume": 44.45714
  },
  {
    "timestamp": 1774924500000,
    "open": 67933.14,
    "high": 68000,
    "low": 67912.1,
    "close": 67912.11,
    "volume": 22.93057
  },
  {
    "timestamp": 1774924800000,
    "open": 67912.11,
    "high": 68000,
    "low": 67902.79,
    "close": 67989.27,
    "volume": 15.28718
  },
  {
    "timestamp": 1774925100000,
    "open": 67989.27,
    "high": 68010,
    "low": 67922.16,
    "close": 67922.17,
    "volume": 28.7658
  }
]